pyndd/__init__.py
pyndd/builder.py
pyndd/parser.py
pyndd-0.4.0.dist-info/METADATA
pyndd-0.4.0.dist-info/WHEEL
pyndd-0.4.0.dist-info/top_level.txt
pyndd-0.4.0.dist-info/RECORD
