Metadata-Version: 2.4
Name: pyndd
Version: 0.4.0
Summary: Python Dynamic DSL for data access and manipulation
Author-email: Your Name <your.email@example.com>
License: MIT
Project-URL: Homepage, https://github.com/yourusername/pyndd
Project-URL: Repository, https://github.com/yourusername/pyndd
Project-URL: Issues, https://github.com/yourusername/pyndd/issues
Keywords: dsl,data,parsing,dynamic
Classifier: Development Status :: 3 - Alpha
Classifier: Intended Audience :: Developers
Classifier: License :: OSI Approved :: MIT License
Classifier: Programming Language :: Python :: 3
Classifier: Programming Language :: Python :: 3.8
Classifier: Programming Language :: Python :: 3.9
Classifier: Programming Language :: Python :: 3.10
Classifier: Programming Language :: Python :: 3.11
Classifier: Programming Language :: Python :: 3.12
Requires-Python: >=3.8
